{
  "date": "2026-06-13",
  "updated_at": "12:09",
  "stats": {
    "total_picks": 11,
    "safes_vip": 0,
    "value_bets": 1,
    "score_moyen": 5.2
  },
  "picks": [
    {
      "home_team": "Brazil",
      "away_team": "Morocco",
      "league": "Coupe du Monde FIFA",
      "time": "22h00",
      "type": "value",
      "score": 3.7,
      "selection": "Brazil gagne",
      "market": "1X2 - 1",
      "odd": 5.95,
      "model_prob": 0.3699,
      "stake_pct": 0.02,
      "tags": [
        "Value +20.2pp edge"
      ],
      "prob_1": 0.3699,
      "prob_x": 0.3516,
      "prob_2": 0.2785,
      "prob_over": 0.2166,
      "odd_1": 5.95,
      "odd_x": 1.22,
      "odd_2": 8.0,
      "odd_over_25": null
    },
    {
      "home_team": "Colo Colo",
      "away_team": "Cobresal",
      "league": "CHI-Primera Division",
      "time": "21h30",
      "type": "grid",
      "score": 7.4,
      "selection": null,
      "market": null,
      "odd": null,
      "model_prob": null,
      "stake_pct": 0.02,
      "tags": [],
      "prob_1": 0.7406,
      "prob_x": 0.1645,
      "prob_2": 0.0948,
      "prob_over": 0.5901,
      "odd_1": 1.23,
      "odd_x": 6.0,
      "odd_2": 8.5,
      "odd_over_25": null
    },
    {
      "home_team": "FC Inter Turku",
      "away_team": "AC Oulu",
      "league": "FIN-Veikkausliiga",
      "time": "12h00",
      "type": "grid",
      "score": 5.8,
      "selection": null,
      "market": null,
      "odd": null,
      "model_prob": null,
      "stake_pct": 0.02,
      "tags": [],
      "prob_1": 0.5834,
      "prob_x": 0.2283,
      "prob_2": 0.1883,
      "prob_over": 0.5137,
      "odd_1": 1.73,
      "odd_x": 3.4,
      "odd_2": 4.33,
      "odd_over_25": null
    },
    {
      "home_team": "Ilves Tampere",
      "away_team": "TPS Turku",
      "league": "FIN-Veikkausliiga",
      "time": "12h00",
      "type": "grid",
      "score": 5.6,
      "selection": null,
      "market": null,
      "odd": null,
      "model_prob": null,
      "stake_pct": 0.02,
      "tags": [],
      "prob_1": 0.5642,
      "prob_x": 0.2321,
      "prob_2": 0.2037,
      "prob_over": 0.5185,
      "odd_1": 1.75,
      "odd_x": 3.5,
      "odd_2": 3.8,
      "odd_over_25": null
    },
    {
      "home_team": "Coquimbo Unido",
      "away_team": "O'Higgins",
      "league": "CHI-Primera Division",
      "time": "16h30",
      "type": "grid",
      "score": 5.6,
      "selection": null,
      "market": null,
      "odd": null,
      "model_prob": null,
      "stake_pct": 0.02,
      "tags": [],
      "prob_1": 0.5596,
      "prob_x": 0.235,
      "prob_2": 0.2054,
      "prob_over": 0.5088,
      "odd_1": 1.8,
      "odd_x": 3.3,
      "odd_2": 3.9,
      "odd_over_25": null
    },
    {
      "home_team": "Qatar",
      "away_team": "Switzerland",
      "league": "Coupe du Monde FIFA",
      "time": "19h00",
      "type": "grid",
      "score": 5.2,
      "selection": null,
      "market": null,
      "odd": null,
      "model_prob": null,
      "stake_pct": 0.02,
      "tags": [],
      "prob_1": 0.1027,
      "prob_x": 0.1859,
      "prob_2": 0.7114,
      "prob_over": 0.5185,
      "odd_1": 16.0,
      "odd_x": 7.0,
      "odd_2": 1.22,
      "odd_over_25": 1.6
    },
    {
      "home_team": "Jaro",
      "away_team": "HJK Helsinki",
      "league": "FIN-Veikkausliiga",
      "time": "14h00",
      "type": "grid",
      "score": 4.9,
      "selection": null,
      "market": null,
      "odd": null,
      "model_prob": null,
      "stake_pct": 0.02,
      "tags": [],
      "prob_1": 0.2256,
      "prob_x": 0.2461,
      "prob_2": 0.5282,
      "prob_over": 0.4866,
      "odd_1": 4.8,
      "odd_x": 3.9,
      "odd_2": 1.61,
      "odd_over_25": null
    },
    {
      "home_team": "FC Lahti",
      "away_team": "SJK Seinäjoki",
      "league": "FIN-Veikkausliiga",
      "time": "16h00",
      "type": "grid",
      "score": 4.9,
      "selection": null,
      "market": null,
      "odd": null,
      "model_prob": null,
      "stake_pct": 0.02,
      "tags": [],
      "prob_1": 0.4722,
      "prob_x": 0.254,
      "prob_2": 0.2739,
      "prob_over": 0.494,
      "odd_1": 2.2,
      "odd_x": 3.3,
      "odd_2": 3.0,
      "odd_over_25": null
    },
    {
      "home_team": "Everton de Viña del Mar",
      "away_team": "Palestino",
      "league": "CHI-Primera Division",
      "time": "19h00",
      "type": "grid",
      "score": 4.9,
      "selection": null,
      "market": null,
      "odd": null,
      "model_prob": null,
      "stake_pct": 0.02,
      "tags": [],
      "prob_1": 0.4257,
      "prob_x": 0.2605,
      "prob_2": 0.3138,
      "prob_over": 0.4866,
      "odd_1": 2.45,
      "odd_x": 3.2,
      "odd_2": 2.65,
      "odd_over_25": null
    },
    {
      "home_team": "IFK Mariehamn",
      "away_team": "IF Gnistan",
      "league": "FIN-Veikkausliiga",
      "time": "16h00",
      "type": "grid",
      "score": 4.8,
      "selection": null,
      "market": null,
      "odd": null,
      "model_prob": null,
      "stake_pct": 0.02,
      "tags": [],
      "prob_1": 0.2841,
      "prob_x": 0.2591,
      "prob_2": 0.4568,
      "prob_over": 0.4791,
      "odd_1": 3.75,
      "odd_x": 3.4,
      "odd_2": 1.85,
      "odd_over_25": null
    },
    {
      "home_team": "VPS Vaasa",
      "away_team": "KuPS Kuopio",
      "league": "FIN-Veikkausliiga",
      "time": "14h00",
      "type": "grid",
      "score": 4.7,
      "selection": null,
      "market": null,
      "odd": null,
      "model_prob": null,
      "stake_pct": 0.02,
      "tags": [],
      "prob_1": 0.3289,
      "prob_x": 0.2665,
      "prob_2": 0.4046,
      "prob_over": 0.4664,
      "odd_1": 3.3,
      "odd_x": 3.1,
      "odd_2": 2.15,
      "odd_over_25": null
    }
  ]
}